README.md
setup.py
lib/nodex/__init__.py
lib/nodex.egg-info/PKG-INFO
lib/nodex.egg-info/SOURCES.txt
lib/nodex.egg-info/dependency_links.txt
lib/nodex.egg-info/not-zip-safe
lib/nodex.egg-info/top_level.txt