Metadata-Version: 2.1
Name: nodex
Version: 0.0.1
Summary: Node Graph OpenImageIO Tool
Home-page: http://github.com/rsgalloway/nodex
Author: Ryan Galloway
Author-email: ryan@rsgalloway.com
License: BSD 3-Clause License
Classifier: Development Status :: 3 - Alpha
Classifier: Intended Audience :: Developers
Classifier: Topic :: Software Development :: Libraries
Classifier: Programming Language :: Python :: 3
Classifier: Programming Language :: Python :: 3.8
Classifier: Programming Language :: Python :: 3.9
Classifier: Programming Language :: Python :: 3.10
Classifier: Programming Language :: Python :: 3.11
Requires-Python: >=3.8
